{
  "asset": "AAPL",
  "start_date": "2023-01-01",
  "end_date": "2025-12-31",
  "initial_equity": 100000,
  "final_equity": 100764.44839516612,
  "total_pl": 764.4483951661399,
  "total_return_pct": 0.7644483951661398,
  "trade_count": 24,
  "win_rate_pct": 75.0,
  "avg_trade_return_pct": 1.656902466876521,
  "sharpe_ratio": 7.918137799588566,
  "best_trade_pct": 7.3845673330859185,
  "worst_trade_pct": -9.375474163173061,
  "trades": [
    {
      "entry_date": "2023-03-16 00:00:00",
      "entry_price": 153.62440490722656,
      "entry_signal": 3.0,
      "quantity": 13.018764832370193,
      "position_value": 2000.0,
      "exit_date": "2023-03-29 00:00:00",
      "exit_price": 158.4741668701172,
      "exit_reason": "TP2 (3%) reached",
      "pl": 63.13791048784711,
      "return_pct": 3.156895524392355,
      "scenario": "WEAK_AT_TP1"
    },
    {
      "entry_date": "2023-03-31 00:00:00",
      "entry_price": 162.54518127441406,
      "entry_signal": 3.0,
      "quantity": 12.312039904961317,
      "position_value": 2001.2627582097568,
      "exit_date": "2023-04-21 00:00:00",
      "exit_price": 162.66348266601562,
      "exit_reason": "Protective SL hit (Scenario A)",
      "pl": 1.4565314542108931,
      "return_pct": 0.07278062054749088,
      "scenario": "WEAK_AT_TP1"
    },
    {
      "entry_date": "2023-04-27 00:00:00",
      "entry_price": 166.0050811767578,
      "entry_signal": 3.0,
      "quantity": 12.055606217907984,
      "position_value": 2001.291888838841,
      "exit_date": "2023-05-05 00:00:00",
      "exit_price": 171.09140014648438,
      "exit_reason": "TP2 (3%) reached",
      "pl": 61.31865859769888,
      "return_pct": 3.0639537860354915,
      "scenario": "WEAK_AT_TP1"
    },
    {
      "entry_date": "2023-05-18 00:00:00",
      "entry_price": 172.78890991210938,
      "entry_signal": 3.0,
      "quantity": 11.589391142228942,
      "position_value": 2002.518262010795,
      "exit_date": "2023-06-02 00:00:00",
      "exit_price": 178.61270141601562,
      "exit_reason": "TP2 (3%) reached",
      "pl": 67.49419766955927,
      "return_pct": 3.3704660252029908,
      "scenario": "WEAK_AT_TP1"
    },
    {
      "entry_date": "2023-06-05 00:00:00",
      "entry_price": 177.26039123535156,
      "entry_signal": 4.0,
      "quantity": 11.304658260082576,
      "position_value": 2003.8681459641862,
      "exit_date": "2023-06-15 00:00:00",
      "exit_price": 183.6073455810547,
      "exit_reason": "TP2 (3%) reached",
      "pl": 71.75014987051983,
      "return_pct": 3.580582385873316,
      "scenario": "WEAK_AT_TP1"
    },
    {
      "entry_date": "2023-06-16 00:00:00",
      "entry_price": 182.5314178466797,
      "entry_signal": 4.0,
      "quantity": 10.986071179515982,
      "position_value": 2005.3031489615967,
      "exit_date": "2023-06-30 00:00:00",
      "exit_price": 191.46453857421875,
      "exit_reason": "TP2 (3%) reached",
      "pl": 98.13990016795373,
      "return_pct": 4.894018154749987,
      "scenario": "WEAK_AT_TP1"
    },
    {
      "entry_date": "2023-07-19 00:00:00",
      "entry_price": 192.57994079589844,
      "entry_signal": 4.0,
      "quantity": 10.423027126653402,
      "position_value": 2007.2659469649557,
      "exit_date": "2023-08-16 00:00:00",
      "exit_price": 174.524658203125,
      "exit_reason": "Sell signal (score -6.0)",
      "pl": -188.1907002438705,
      "return_pct": -9.375474163173061,
      "scenario": "UNKNOWN"
    },
    {
      "entry_date": "2023-11-14 00:00:00",
      "entry_price": 185.51278686523438,
      "entry_signal": 2.0,
      "quantity": 10.799806130967786,
      "position_value": 2003.5021329600784,
      "exit_date": "2023-12-05 00:00:00",
      "exit_price": 191.4313201904297,
      "exit_reason": "TP2 (3%) reached",
      "pl": 63.919012491781494,
      "return_pct": 3.1903640849807435,
      "scenario": "WEAK_AT_TP1"
    },
    {
      "entry_date": "2023-12-07 00:00:00",
      "entry_price": 192.27256774902344,
      "entry_signal": 3.0,
      "quantity": 10.42676309304189,
      "position_value": 2004.7805132099138,
      "exit_date": "2023-12-20 00:00:00",
      "exit_price": 192.8268280029297,
      "exit_reason": "Protective SL hit (Scenario A)",
      "pl": 5.779140359369714,
      "return_pct": 0.28826798351688687,
      "scenario": "WEAK_AT_TP1"
    },
    {
      "entry_date": "2024-05-13 00:00:00",
      "entry_price": 184.85037231445312,
      "entry_signal": 2.0,
      "quantity": 10.846048460246147,
      "position_value": 2004.8960960171014,
      "exit_date": "2024-05-21 00:00:00",
      "exit_price": 190.87379455566406,
      "exit_reason": "TP2 (3%) reached",
      "pl": 65.33032952469829,
      "return_pct": 3.258539415308485,
      "scenario": "WEAK_AT_TP1"
    },
    {
      "entry_date": "2024-05-31 00:00:00",
      "entry_price": 190.77455139160156,
      "entry_signal": 2.0,
      "quantity": 10.516091837057855,
      "position_value": 2006.2027026075955,
      "exit_date": "2024-06-10 00:00:00",
      "exit_price": 191.63787841796875,
      "exit_reason": "Protective SL hit (Scenario A)",
      "pl": 9.078826294691412,
      "return_pct": 0.4525378359271003,
      "scenario": "WEAK_AT_TP1"
    },
    {
      "entry_date": "2024-06-11 00:00:00",
      "entry_price": 205.56016540527344,
      "entry_signal": 4.0,
      "quantity": 9.760569491553918,
      "position_value": 2006.3842791334891,
      "exit_date": "2024-06-13 00:00:00",
      "exit_price": 212.59579467773438,
      "exit_reason": "TP2 (3%) reached",
      "pl": 68.67174843066591,
      "return_pct": 3.4226618073544546,
      "scenario": "WEAK_AT_TP1"
    },
    {
      "entry_date": "2024-06-14 00:00:00",
      "entry_price": 210.8592071533203,
      "entry_signal": 3.0,
      "quantity": 9.52179295942348,
      "position_value": 2007.7577141021027,
      "exit_date": "2024-06-20 00:00:00",
      "exit_price": 208.07077026367188,
      "exit_reason": "Protective SL hit (Scenario A)",
      "pl": -26.550918743651202,
      "return_pct": -1.3224164727229124,
      "scenario": "WEAK_AT_TP1"
    },
    {
      "entry_date": "2024-06-21 00:00:00",
      "entry_price": 205.89761352539062,
      "entry_signal": 2.0,
      "quantity": 9.748664209163866,
      "position_value": 2007.2266957272295,
      "exit_date": "2024-06-27 00:00:00",
      "exit_price": 212.45687866210938,
      "exit_reason": "TP2 (3%) reached",
      "pl": 63.944073276746416,
      "return_pct": 3.1856926481131276,
      "scenario": "WEAK_AT_TP1"
    },
    {
      "entry_date": "2024-08-29 00:00:00",
      "entry_price": 228.29037475585938,
      "entry_signal": 2.0,
      "quantity": 8.798030049846476,
      "position_value": 2008.5055771927643,
      "exit_date": "2024-10-07 00:00:00",
      "exit_price": 220.2432403564453,
      "exit_reason": "Sell signal (score -5.0)",
      "pl": -70.7989302611982,
      "return_pct": -3.5249556219879663,
      "scenario": "UNKNOWN"
    },
    {
      "entry_date": "2024-10-15 00:00:00",
      "entry_price": 232.3238983154297,
      "entry_signal": 3.0,
      "quantity": 8.639186984812403,
      "position_value": 2007.0895985875404,
      "exit_date": "2024-12-03 00:00:00",
      "exit_price": 241.33168029785156,
      "exit_reason": "TP2 (3%) reached",
      "pl": 77.81991286456673,
      "return_pct": 3.877251564620301,
      "scenario": "WEAK_AT_TP1"
    },
    {
      "entry_date": "2024-12-04 00:00:00",
      "entry_price": 241.68971252441406,
      "entry_signal": 2.0,
      "quantity": 8.31084606731836,
      "position_value": 2008.6459968448316,
      "exit_date": "2024-12-16 00:00:00",
      "exit_price": 249.67608642578125,
      "exit_reason": "TP2 (3%) reached",
      "pl": 66.37352413031148,
      "return_pct": 3.30439132801751,
      "scenario": "WEAK_AT_TP1"
    },
    {
      "entry_date": "2024-12-17 00:00:00",
      "entry_price": 252.1028289794922,
      "entry_signal": 3.0,
      "quantity": 7.972831861759644,
      "position_value": 2009.973467327438,
      "exit_date": "2024-12-30 00:00:00",
      "exit_price": 250.82980346679688,
      "exit_reason": "Protective SL hit (Scenario A)",
      "pl": -10.149618368450094,
      "return_pct": -0.5049628034118052,
      "scenario": "WEAK_AT_TP1"
    },
    {
      "entry_date": "2025-08-06 00:00:00",
      "entry_price": 212.60302734375,
      "entry_signal": 2.0,
      "quantity": 9.453160192825218,
      "position_value": 2009.770474960069,
      "exit_date": "2025-08-07 00:00:00",
      "exit_price": 219.36245727539062,
      "exit_reason": "TP2 (3%) reached",
      "pl": 63.89797395597644,
      "return_pct": 3.179366736256089,
      "scenario": "WEAK_AT_TP1"
    },
    {
      "entry_date": "2025-08-08 00:00:00",
      "entry_price": 228.65419006347656,
      "entry_signal": 4.0,
      "quantity": 8.79515233847629,
      "position_value": 2011.0484344391882,
      "exit_date": "2025-08-19 00:00:00",
      "exit_price": 230.1213836669922,
      "exit_reason": "Protective SL hit (Scenario A)",
      "pl": 12.904191252957904,
      "return_pct": 0.6416648665429302,
      "scenario": "WEAK_AT_TP1"
    },
    {
      "entry_date": "2025-09-03 00:00:00",
      "entry_price": 238.01634216308594,
      "entry_signal": 3.0,
      "quantity": 8.450287488604982,
      "position_value": 2011.3065182642476,
      "exit_date": "2025-09-22 00:00:00",
      "exit_price": 255.5928192138672,
      "exit_reason": "TP2 (3%) reached",
      "pl": 148.5262841159694,
      "return_pct": 7.3845673330859185,
      "scenario": "WEAK_AT_TP1"
    },
    {
      "entry_date": "2025-10-20 00:00:00",
      "entry_price": 261.7411193847656,
      "entry_signal": 4.0,
      "quantity": 7.695684379593151,
      "position_value": 2014.277043946567,
      "exit_date": "2025-10-30 00:00:00",
      "exit_price": 270.8836669921875,
      "exit_reason": "TP2 (3%) reached",
      "pl": 70.35816081212326,
      "return_pct": 3.4929733734278536,
      "scenario": "WEAK_AT_TP1"
    },
    {
      "entry_date": "2025-10-31 00:00:00",
      "entry_price": 269.85565185546875,
      "entry_signal": 4.0,
      "quantity": 7.469490423133268,
      "position_value": 2015.6842071628093,
      "exit_date": "2025-11-17 00:00:00",
      "exit_price": 267.2099609375,
      "exit_reason": "Protective SL hit (Scenario A)",
      "pl": -19.761962974338243,
      "return_pct": -0.9804096744972932,
      "scenario": "WEAK_AT_TP1"
    },
    {
      "entry_date": "2025-12-01 00:00:00",
      "entry_price": 282.8353576660156,
      "entry_signal": 3.0,
      "quantity": 7.125307756900266,
      "position_value": 2015.2889679033224
    }
  ],
  "timestamp": "2026-03-12T00:23:53.680982"
}